{
    "b7ad3f32-a42e-a95d-5966-d19eb6d6edcc": {
        "paletteKey": "FlexLayoutCol",
        "commentid": null,
        "designerReference": [
            {
                "_key": "componentLabel",
                "_value": "Column",
                "_type": "kv",
                "_attrDef": "p",
                "_useAsLabel": true
            },
            {
                "_key": "style",
                "_value": "",
                "_type": "kv",
                "_attrDef": "p"
            },
            {
                "_key": "class",
                "_value": "",
                "_type": "dav",
                "_attrDef": "p"
            },
            {
                "_key": "fxFlex",
                "_value": "",
                "_type": "kv",
                "_attrDef": "p"
            },
            {
                "_key": "fxLayoutGap",
                "_value": "1em",
                "_type": "kv",
                "_attrDef": "p"
            },
            {
                "_key": "wrap",
                "_value": "wrap",
                "_type": "a",
                "_attrDef": "p"
            },
            {
                "_key": "layoutAlign",
                "_value": "start",
                "_type": "a",
                "_attrDef": "p"
            },
            {
                "_key": "pLayoutAlign",
                "_value": "stretch",
                "_type": "a",
                "_attrDef": "p"
            },
            {
                "_key": "[fxShow]",
                "_value": "true",
                "_type": "kv",
                "_attrDef": "p"
            }
        ],
        "5d80f98b-689d-fa36-5b64-57d8f2e3b396": {
            "paletteKey": "FlexLayoutRow",
            "parentEditorKey": "b7ad3f32-a42e-a95d-5966-d19eb6d6edcc",
            "commentid": null,
            "designerReference": [
                {
                    "_key": "componentLabel",
                    "_value": "Row",
                    "_type": "kv",
                    "_attrDef": "p",
                    "_useAsLabel": true
                },
                {
                    "_key": "style",
                    "_value": "",
                    "_type": "kv",
                    "_attrDef": "p"
                },
                {
                    "_key": "class",
                    "_value": "",
                    "_type": "dav",
                    "_attrDef": "p"
                },
                {
                    "_key": "fxFlex",
                    "_value": "",
                    "_type": "kv",
                    "_attrDef": "p"
                },
                {
                    "_key": "fxLayoutGap",
                    "_value": "",
                    "_type": "kv",
                    "_attrDef": "p"
                },
                {
                    "_key": "wrap",
                    "_value": "wrap",
                    "_type": "a",
                    "_attrDef": "p"
                },
                {
                    "_key": "layoutAlign",
                    "_value": "center",
                    "_type": "a",
                    "_attrDef": "p"
                },
                {
                    "_key": "pLayoutAlign",
                    "_value": "center",
                    "_type": "a",
                    "_attrDef": "p"
                },
                {
                    "_key": "[fxShow]",
                    "_value": "true",
                    "_type": "kv",
                    "_attrDef": "p"
                }
            ],
            "d78e9f35-0bb1-6249-0e31-7bada69fe219": {
                "paletteKey": "FlexLayoutCol",
                "parentEditorKey": "5d80f98b-689d-fa36-5b64-57d8f2e3b396",
                "commentid": null,
                "designerReference": [
                    {
                        "_key": "componentLabel",
                        "_value": "Column",
                        "_type": "kv",
                        "_attrDef": "p",
                        "_useAsLabel": true
                    },
                    {
                        "_key": "style",
                        "_value": "",
                        "_type": "kv",
                        "_attrDef": "p"
                    },
                    {
                        "_key": "class",
                        "_value": "",
                        "_type": "dav",
                        "_attrDef": "p"
                    },
                    {
                        "_key": "fxFlex",
                        "_value": "",
                        "_type": "kv",
                        "_attrDef": "p"
                    },
                    {
                        "_key": "fxLayoutGap",
                        "_value": "",
                        "_type": "kv",
                        "_attrDef": "p"
                    },
                    {
                        "_key": "wrap",
                        "_value": "wrap",
                        "_type": "a",
                        "_attrDef": "p"
                    },
                    {
                        "_key": "layoutAlign",
                        "_value": "center",
                        "_type": "a",
                        "_attrDef": "p"
                    },
                    {
                        "_key": "pLayoutAlign",
                        "_value": "center",
                        "_type": "a",
                        "_attrDef": "p"
                    },
                    {
                        "_key": "[fxShow]",
                        "_value": "true",
                        "_type": "kv",
                        "_attrDef": "p"
                    }
                ],
                "6c929880-60db-820b-c924-958d598c10d3": {
                    "paletteKey": "Html5",
                    "parentEditorKey": "d78e9f35-0bb1-6249-0e31-7bada69fe219",
                    "isAdvancedComponent": true,
                    "commentid": null,
                    "designerReference": [
                        {
                            "_key": "style",
                            "_value": "",
                            "_type": "kv",
                            "_attrDef": "p"
                        },
                        {
                            "_key": "class",
                            "_value": [
                                "topTitle"
                            ],
                            "_type": "dav",
                            "_attrDef": "p"
                        },
                        {
                            "_key": "htmlElement",
                            "_value": "h2",
                            "_type": "dav",
                            "_attrDef": "p",
                            "_useAsLabel": true
                        },
                        {
                            "_key": "tagType",
                            "_value": "h2",
                            "_type": "a",
                            "_attrDef": "p",
                            "_visibility": false
                        },
                        {
                            "_key": "name",
                            "_value": "",
                            "_type": "kv",
                            "_attrDef": "p",
                            "_visibility": false
                        },
                        {
                            "_key": "sandbox",
                            "_value": "",
                            "_type": "kv",
                            "_attrDef": "p",
                            "_visibility": false
                        },
                        {
                            "_key": "src",
                            "_value": "",
                            "_type": "kv",
                            "_attrDef": "p",
                            "_visibility": false
                        },
                        {
                            "_key": "srcdoc",
                            "_value": "",
                            "_type": "kv",
                            "_attrDef": "p",
                            "_visibility": false
                        },
                        {
                            "_key": "width",
                            "_value": "",
                            "_type": "kv",
                            "_attrDef": "p",
                            "_visibility": false
                        },
                        {
                            "_key": "[autoplay]",
                            "_value": "",
                            "_type": "kv",
                            "_attrDef": "p",
                            "_visibility": false
                        },
                        {
                            "_key": "[loop]",
                            "_value": "",
                            "_type": "kv",
                            "_attrDef": "p",
                            "_visibility": false
                        },
                        {
                            "_key": "data",
                            "_value": "",
                            "_type": "kv",
                            "_attrDef": "p",
                            "_visibility": false
                        },
                        {
                            "_key": "audioSource",
                            "_value": [],
                            "_type": "a",
                            "_attrDef": "p",
                            "_visibility": false
                        },
                        {
                            "_key": "videoSource",
                            "_value": [],
                            "_type": "a",
                            "_attrDef": "p",
                            "_visibility": false
                        },
                        {
                            "_key": "audioDatasource",
                            "_value": "",
                            "_type": "a",
                            "_attrDef": "p",
                            "_visibility": false
                        },
                        {
                            "_key": "audioSrc",
                            "_value": "",
                            "_type": "a",
                            "_attrDef": "p",
                            "_visibility": false
                        },
                        {
                            "_key": "audioType",
                            "_value": "",
                            "_type": "a",
                            "_attrDef": "p",
                            "_visibility": false
                        },
                        {
                            "_key": "videoDatasource",
                            "_value": "",
                            "_type": "a",
                            "_attrDef": "p",
                            "_visibility": false
                        },
                        {
                            "_key": "videoSrc",
                            "_value": "",
                            "_type": "a",
                            "_attrDef": "p",
                            "_visibility": false
                        },
                        {
                            "_key": "videoType",
                            "_value": "",
                            "_type": "a",
                            "_attrDef": "p",
                            "_visibility": false
                        },
                        {
                            "_key": "(audioplay)",
                            "_value": "",
                            "_type": "a",
                            "_attrDef": "p",
                            "_visibility": false
                        },
                        {
                            "_key": "(videoplay)",
                            "_value": "",
                            "_type": "a",
                            "_attrDef": "p",
                            "_visibility": false
                        },
                        {
                            "_key": "(audiopause)",
                            "_value": "",
                            "_type": "kv",
                            "_attrDef": "p",
                            "_visibility": false
                        },
                        {
                            "_key": "(videopause)",
                            "_value": "",
                            "_type": "kv",
                            "_attrDef": "p",
                            "_visibility": false
                        },
                        {
                            "_key": "(audioended)",
                            "_value": "",
                            "_type": "kv",
                            "_attrDef": "p",
                            "_visibility": false
                        },
                        {
                            "_key": "(videoended)",
                            "_value": "",
                            "_type": "kv",
                            "_attrDef": "p",
                            "_visibility": false
                        }
                    ],
                    "9c6adf49-5d5d-8af6-1732-b8c6b29325fc": {
                        "paletteKey": "html-editor",
                        "parentEditorKey": "6c929880-60db-820b-c924-958d598c10d3",
                        "isAdvancedChildComponent": true,
                        "commentid": null,
                        "designerReference": [
                            {
                                "_key": "style",
                                "_value": "",
                                "_type": "kv",
                                "_attrDef": "p"
                            },
                            {
                                "_key": "class",
                                "_value": "",
                                "_type": "dav",
                                "_attrDef": "p"
                            },
                            {
                                "_key": "html",
                                "_value": "How can we help you?",
                                "_type": "a",
                                "_attrDef": "p"
                            }
                        ]
                    }
                },
                "de5e84d4-0c84-905e-086a-30ba599ebbc8": {
                    "paletteKey": "Html5",
                    "parentEditorKey": "d78e9f35-0bb1-6249-0e31-7bada69fe219",
                    "isAdvancedComponent": true,
                    "commentid": null,
                    "designerReference": [
                        {
                            "_key": "style",
                            "_value": "",
                            "_type": "kv",
                            "_attrDef": "p"
                        },
                        {
                            "_key": "class",
                            "_value": [
                                "selectAllAply"
                            ],
                            "_type": "dav",
                            "_attrDef": "p"
                        },
                        {
                            "_key": "htmlElement",
                            "_value": "p",
                            "_type": "dav",
                            "_attrDef": "p",
                            "_useAsLabel": true
                        },
                        {
                            "_key": "tagType",
                            "_value": "p",
                            "_type": "a",
                            "_attrDef": "p",
                            "_visibility": false
                        },
                        {
                            "_key": "name",
                            "_value": "",
                            "_type": "kv",
                            "_attrDef": "p",
                            "_visibility": false
                        },
                        {
                            "_key": "sandbox",
                            "_value": "",
                            "_type": "kv",
                            "_attrDef": "p",
                            "_visibility": false
                        },
                        {
                            "_key": "src",
                            "_value": "",
                            "_type": "kv",
                            "_attrDef": "p",
                            "_visibility": false
                        },
                        {
                            "_key": "srcdoc",
                            "_value": "",
                            "_type": "kv",
                            "_attrDef": "p",
                            "_visibility": false
                        },
                        {
                            "_key": "width",
                            "_value": "",
                            "_type": "kv",
                            "_attrDef": "p",
                            "_visibility": false
                        },
                        {
                            "_key": "[autoplay]",
                            "_value": "",
                            "_type": "kv",
                            "_attrDef": "p",
                            "_visibility": false
                        },
                        {
                            "_key": "[loop]",
                            "_value": "",
                            "_type": "kv",
                            "_attrDef": "p",
                            "_visibility": false
                        },
                        {
                            "_key": "data",
                            "_value": "",
                            "_type": "kv",
                            "_attrDef": "p",
                            "_visibility": false
                        },
                        {
                            "_key": "audioSource",
                            "_value": [],
                            "_type": "a",
                            "_attrDef": "p",
                            "_visibility": false
                        },
                        {
                            "_key": "videoSource",
                            "_value": [],
                            "_type": "a",
                            "_attrDef": "p",
                            "_visibility": false
                        },
                        {
                            "_key": "audioDatasource",
                            "_value": "",
                            "_type": "a",
                            "_attrDef": "p",
                            "_visibility": false
                        },
                        {
                            "_key": "audioSrc",
                            "_value": "",
                            "_type": "a",
                            "_attrDef": "p",
                            "_visibility": false
                        },
                        {
                            "_key": "audioType",
                            "_value": "",
                            "_type": "a",
                            "_attrDef": "p",
                            "_visibility": false
                        },
                        {
                            "_key": "videoDatasource",
                            "_value": "",
                            "_type": "a",
                            "_attrDef": "p",
                            "_visibility": false
                        },
                        {
                            "_key": "videoSrc",
                            "_value": "",
                            "_type": "a",
                            "_attrDef": "p",
                            "_visibility": false
                        },
                        {
                            "_key": "videoType",
                            "_value": "",
                            "_type": "a",
                            "_attrDef": "p",
                            "_visibility": false
                        },
                        {
                            "_key": "(audioplay)",
                            "_value": "",
                            "_type": "a",
                            "_attrDef": "p",
                            "_visibility": false
                        },
                        {
                            "_key": "(videoplay)",
                            "_value": "",
                            "_type": "a",
                            "_attrDef": "p",
                            "_visibility": false
                        },
                        {
                            "_key": "(audiopause)",
                            "_value": "",
                            "_type": "kv",
                            "_attrDef": "p",
                            "_visibility": false
                        },
                        {
                            "_key": "(videopause)",
                            "_value": "",
                            "_type": "kv",
                            "_attrDef": "p",
                            "_visibility": false
                        },
                        {
                            "_key": "(audioended)",
                            "_value": "",
                            "_type": "kv",
                            "_attrDef": "p",
                            "_visibility": false
                        },
                        {
                            "_key": "(videoended)",
                            "_value": "",
                            "_type": "kv",
                            "_attrDef": "p",
                            "_visibility": false
                        }
                    ],
                    "06b61df7-6983-01be-6fe5-92e4a5930f75": {
                        "paletteKey": "html-editor",
                        "parentEditorKey": "de5e84d4-0c84-905e-086a-30ba599ebbc8",
                        "isAdvancedChildComponent": true,
                        "commentid": null,
                        "designerReference": [
                            {
                                "_key": "style",
                                "_value": "",
                                "_type": "kv",
                                "_attrDef": "p"
                            },
                            {
                                "_key": "class",
                                "_value": "",
                                "_type": "dav",
                                "_attrDef": "p"
                            },
                            {
                                "_key": "html",
                                "_value": "Select all that applay",
                                "_type": "a",
                                "_attrDef": "p"
                            }
                        ]
                    }
                }
            }
        },
        "4a0e81ca-fe88-9f5b-d5d3-e5e9dcec8ff4": {
            "paletteKey": "FlexLayoutRow",
            "parentEditorKey": "b7ad3f32-a42e-a95d-5966-d19eb6d6edcc",
            "commentid": null,
            "designerReference": [
                {
                    "_key": "componentLabel",
                    "_value": "Row",
                    "_type": "kv",
                    "_attrDef": "p",
                    "_useAsLabel": true
                },
                {
                    "_key": "style",
                    "_value": "",
                    "_type": "kv",
                    "_attrDef": "p"
                },
                {
                    "_key": "class",
                    "_value": "",
                    "_type": "dav",
                    "_attrDef": "p"
                },
                {
                    "_key": "fxFlex",
                    "_value": "",
                    "_type": "kv",
                    "_attrDef": "p"
                },
                {
                    "_key": "fxLayoutGap",
                    "_value": "10px",
                    "_type": "kv",
                    "_attrDef": "p"
                },
                {
                    "_key": "wrap",
                    "_value": "wrap",
                    "_type": "a",
                    "_attrDef": "p"
                },
                {
                    "_key": "layoutAlign",
                    "_value": "center",
                    "_type": "a",
                    "_attrDef": "p"
                },
                {
                    "_key": "pLayoutAlign",
                    "_value": "center",
                    "_type": "a",
                    "_attrDef": "p"
                },
                {
                    "_key": "[fxShow]",
                    "_value": "true",
                    "_type": "kv",
                    "_attrDef": "p"
                }
            ],
            "c1fe23a5-3b7d-61ce-0bc8-27e5cbdd844f": {
                "paletteKey": "FlexLayoutCol",
                "parentEditorKey": "4a0e81ca-fe88-9f5b-d5d3-e5e9dcec8ff4",
                "commentid": null,
                "designerReference": [
                    {
                        "_key": "componentLabel",
                        "_value": "Column",
                        "_type": "kv",
                        "_attrDef": "p",
                        "_useAsLabel": true
                    },
                    {
                        "_key": "style",
                        "_value": "",
                        "_type": "kv",
                        "_attrDef": "p"
                    },
                    {
                        "_key": "class",
                        "_value": [],
                        "_type": "dav",
                        "_attrDef": "p"
                    },
                    {
                        "_key": "fxFlex",
                        "_value": "160px",
                        "_type": "kv",
                        "_attrDef": "p"
                    },
                    {
                        "_key": "fxLayoutGap",
                        "_value": "",
                        "_type": "kv",
                        "_attrDef": "p"
                    },
                    {
                        "_key": "wrap",
                        "_value": "wrap",
                        "_type": "a",
                        "_attrDef": "p"
                    },
                    {
                        "_key": "layoutAlign",
                        "_value": "center",
                        "_type": "a",
                        "_attrDef": "p"
                    },
                    {
                        "_key": "pLayoutAlign",
                        "_value": "center",
                        "_type": "a",
                        "_attrDef": "p"
                    },
                    {
                        "_key": "[fxShow]",
                        "_value": "true",
                        "_type": "kv",
                        "_attrDef": "p"
                    },
                    {
                        "_key": "*ngFor",
                        "_value": "let data of select_plan",
                        "_type": "kv",
                        "_attrDef": "c"
                    }
                ],
                "f28237cc-2920-7e58-b067-f26c899e26aa": {
                    "paletteKey": "NG-icon",
                    "parentEditorKey": "c1fe23a5-3b7d-61ce-0bc8-27e5cbdd844f",
                    "commentid": null,
                    "designerReference": [
                        {
                            "_key": "style",
                            "_value": "",
                            "_type": "kv",
                            "_attrDef": "p"
                        },
                        {
                            "_key": "class",
                            "_value": [
                                "bodyIcons"
                            ],
                            "_type": "dav",
                            "_attrDef": "p"
                        },
                        {
                            "_key": "IconName",
                            "_value": "{{data.icon}}",
                            "_type": "a",
                            "_attrDef": "p",
                            "_useAsLabel": true
                        },
                        {
                            "_key": "[inline]",
                            "_value": "",
                            "_type": "kv",
                            "_attrDef": "p"
                        },
                        {
                            "_key": "color",
                            "_value": "",
                            "_type": "kv",
                            "_attrDef": "p"
                        }
                    ]
                },
                "56511f42-f3e6-eab4-483c-6bcbc77c6d13": {
                    "paletteKey": "Html5",
                    "parentEditorKey": "c1fe23a5-3b7d-61ce-0bc8-27e5cbdd844f",
                    "isAdvancedComponent": true,
                    "commentid": null,
                    "designerReference": [
                        {
                            "_key": "style",
                            "_value": "",
                            "_type": "kv",
                            "_attrDef": "p"
                        },
                        {
                            "_key": "class",
                            "_value": "",
                            "_type": "dav",
                            "_attrDef": "p"
                        },
                        {
                            "_key": "htmlElement",
                            "_value": "label",
                            "_type": "dav",
                            "_attrDef": "p",
                            "_useAsLabel": true
                        },
                        {
                            "_key": "tagType",
                            "_value": "label",
                            "_type": "a",
                            "_attrDef": "p",
                            "_visibility": false
                        },
                        {
                            "_key": "name",
                            "_value": "",
                            "_type": "kv",
                            "_attrDef": "p",
                            "_visibility": false
                        },
                        {
                            "_key": "sandbox",
                            "_value": "",
                            "_type": "kv",
                            "_attrDef": "p",
                            "_visibility": false
                        },
                        {
                            "_key": "src",
                            "_value": "",
                            "_type": "kv",
                            "_attrDef": "p",
                            "_visibility": false
                        },
                        {
                            "_key": "srcdoc",
                            "_value": "",
                            "_type": "kv",
                            "_attrDef": "p",
                            "_visibility": false
                        },
                        {
                            "_key": "width",
                            "_value": "",
                            "_type": "kv",
                            "_attrDef": "p",
                            "_visibility": false
                        },
                        {
                            "_key": "[autoplay]",
                            "_value": "",
                            "_type": "kv",
                            "_attrDef": "p",
                            "_visibility": false
                        },
                        {
                            "_key": "[loop]",
                            "_value": "",
                            "_type": "kv",
                            "_attrDef": "p",
                            "_visibility": false
                        },
                        {
                            "_key": "data",
                            "_value": "",
                            "_type": "kv",
                            "_attrDef": "p",
                            "_visibility": false
                        },
                        {
                            "_key": "audioSource",
                            "_value": [],
                            "_type": "a",
                            "_attrDef": "p",
                            "_visibility": false
                        },
                        {
                            "_key": "videoSource",
                            "_value": [],
                            "_type": "a",
                            "_attrDef": "p",
                            "_visibility": false
                        },
                        {
                            "_key": "audioDatasource",
                            "_value": "",
                            "_type": "a",
                            "_attrDef": "p",
                            "_visibility": false
                        },
                        {
                            "_key": "audioSrc",
                            "_value": "",
                            "_type": "a",
                            "_attrDef": "p",
                            "_visibility": false
                        },
                        {
                            "_key": "audioType",
                            "_value": "",
                            "_type": "a",
                            "_attrDef": "p",
                            "_visibility": false
                        },
                        {
                            "_key": "videoDatasource",
                            "_value": "",
                            "_type": "a",
                            "_attrDef": "p",
                            "_visibility": false
                        },
                        {
                            "_key": "videoSrc",
                            "_value": "",
                            "_type": "a",
                            "_attrDef": "p",
                            "_visibility": false
                        },
                        {
                            "_key": "videoType",
                            "_value": "",
                            "_type": "a",
                            "_attrDef": "p",
                            "_visibility": false
                        },
                        {
                            "_key": "(audioplay)",
                            "_value": "",
                            "_type": "a",
                            "_attrDef": "p",
                            "_visibility": false
                        },
                        {
                            "_key": "(videoplay)",
                            "_value": "",
                            "_type": "a",
                            "_attrDef": "p",
                            "_visibility": false
                        },
                        {
                            "_key": "(audiopause)",
                            "_value": "",
                            "_type": "kv",
                            "_attrDef": "p",
                            "_visibility": false
                        },
                        {
                            "_key": "(videopause)",
                            "_value": "",
                            "_type": "kv",
                            "_attrDef": "p",
                            "_visibility": false
                        },
                        {
                            "_key": "(audioended)",
                            "_value": "",
                            "_type": "kv",
                            "_attrDef": "p",
                            "_visibility": false
                        },
                        {
                            "_key": "(videoended)",
                            "_value": "",
                            "_type": "kv",
                            "_attrDef": "p",
                            "_visibility": false
                        }
                    ],
                    "21b1c4af-6f80-43cb-099c-129aceca7921": {
                        "paletteKey": "html-editor",
                        "parentEditorKey": "56511f42-f3e6-eab4-483c-6bcbc77c6d13",
                        "isAdvancedChildComponent": true,
                        "commentid": null,
                        "designerReference": [
                            {
                                "_key": "style",
                                "_value": "",
                                "_type": "kv",
                                "_attrDef": "p"
                            },
                            {
                                "_key": "class",
                                "_value": "",
                                "_type": "dav",
                                "_attrDef": "p"
                            },
                            {
                                "_key": "html",
                                "_value": "{{data.paragraph}}",
                                "_type": "a",
                                "_attrDef": "p"
                            }
                        ]
                    }
                },
                "bcbee5b7-7a6b-cdb7-b7b0-2872f17f089e": {
                    "paletteKey": "NG-checkbox",
                    "parentEditorKey": "c1fe23a5-3b7d-61ce-0bc8-27e5cbdd844f",
                    "commentid": null,
                    "designerReference": [
                        {
                            "_key": "style",
                            "_value": "",
                            "_type": "kv",
                            "_attrDef": "p"
                        },
                        {
                            "_key": "class",
                            "_value": "",
                            "_type": "dav",
                            "_attrDef": "p"
                        },
                        {
                            "_key": "componentLabel",
                            "_value": "Checkbox",
                            "_type": "kv",
                            "_attrDef": "p",
                            "_useAsLabel": true
                        },
                        {
                            "_key": "value",
                            "_value": "",
                            "_type": "kv",
                            "_attrDef": "p"
                        },
                        {
                            "_key": "[required]",
                            "_value": "false",
                            "_type": "kv",
                            "_attrDef": "p"
                        },
                        {
                            "_key": "[(ngModel)]",
                            "_value": "",
                            "_type": "kv",
                            "_attrDef": "p"
                        },
                        {
                            "_key": "label",
                            "_value": "",
                            "_type": "a",
                            "_attrDef": "p"
                        },
                        {
                            "_key": "id",
                            "_value": "",
                            "_type": "kv",
                            "_attrDef": "p"
                        },
                        {
                            "_key": "name",
                            "_value": "",
                            "_type": "kv",
                            "_attrDef": "p"
                        },
                        {
                            "_key": "labelPosition",
                            "_value": "",
                            "_type": "kv",
                            "_attrDef": "p"
                        },
                        {
                            "_key": "color",
                            "_value": "",
                            "_type": "kv",
                            "_attrDef": "p"
                        },
                        {
                            "_key": "[checked]",
                            "_value": "",
                            "_type": "kv",
                            "_attrDef": "p"
                        },
                        {
                            "_key": "(change)",
                            "_value": "",
                            "_type": "kv",
                            "_attrDef": "p"
                        },
                        {
                            "_key": "[disabled]",
                            "_value": "",
                            "_type": "kv",
                            "_attrDef": "p"
                        },
                        {
                            "_key": "[disableRipple]",
                            "_value": "",
                            "_type": "kv",
                            "_attrDef": "p"
                        },
                        {
                            "_key": "[indeterminate]",
                            "_value": "",
                            "_type": "kv",
                            "_attrDef": "p"
                        }
                    ]
                }
            }
        }
    }
}
